pyudmx/__init__.py
pyudmx/pyudmx.py
udmx_pyusb-2.0.0.dist-info/METADATA
udmx_pyusb-2.0.0.dist-info/RECORD
udmx_pyusb-2.0.0.dist-info/WHEEL
udmx_pyusb-2.0.0.dist-info/top_level.txt
