Metadata-Version: 2.1
Name: udmx-pyusb
Version: 2.0.0
Summary: uDMX Interface Library
Home-page: https://www.github.com/dhocker/udmx-pyusb
Author: Dave Hocker
Author-email: AtHomeX10@gmail.com
License: GPLv3. See LICENSE file.
Platform: UNKNOWN
Classifier: Programming Language :: Python :: 3
Classifier: Operating System :: OS Independent
